pyservice_django-1.1.81.dist-info/DESCRIPTION.rst
pyservice_django-1.1.81.dist-info/RECORD
pyservice_django-1.1.81.dist-info/top_level.txt
pyservice_django-1.1.81.dist-info/WHEEL
pyservice_django-1.1.81.dist-info/metadata.json
pyservice_django-1.1.81.dist-info/METADATA
django_project/manage.py
django_project/__init__.py
django_project/pyservice/models.py
django_project/pyservice/__init__.py
django_project/pyservice/tests/i18n_pt_br.py
django_project/pyservice/tests/test_database_methods.py
django_project/pyservice/tests/test_pyservice_django.py
django_project/pyservice/tests/test_config.py
django_project/pyservice/tests/__init__.py
django_project/pyservice/tests/i18n/i18n_pt_br.py
django_project/pyservice/tests/i18n/__init__.py
django_project/service/urls.py
django_project/service/wsgi.py
django_project/service/settings.py
django_project/service/__init__.py
pyservice_django/pyservice_django.py
pyservice_django/config.py
pyservice_django/__init__.py
tests/i18n_pt_br.py
tests/test_pyservice_django.py
tests/__init__.py
tests/i18n/i18n_pt_br.py
tests/i18n/__init__.py
