Metadata-Version: 2.0
Name: pyservice-django
Version: 1.1.81
Summary: UNKNOWN
Home-page: https://github.com/rodrigorodriguescosta/pyservice_django
Author: Rodrigo Rodrigues
Author-email: rodrigorodriguescosta@gmail.com
License: MIT
Platform: UNKNOWN
Classifier: Development Status :: 4 - Beta
Classifier: Intended Audience :: Developers
Classifier: Topic :: Software Development :: Build Tools
Classifier: License :: OSI Approved :: MIT License
Classifier: Programming Language :: Python :: 2
Classifier: Programming Language :: Python :: 2.6
Classifier: Programming Language :: Python :: 2.7
Classifier: Programming Language :: Python :: 3
Classifier: Programming Language :: Python :: 3.3
Classifier: Programming Language :: Python :: 3.4
Classifier: Programming Language :: Python :: 3.5
Requires-Dist: django (==1.8)
